liteagents/__init__.py
liteagents/main.py
liteagents-0.0.2.dist-info/METADATA
liteagents-0.0.2.dist-info/WHEEL
liteagents-0.0.2.dist-info/RECORD
